Metadata-Version: 1.1
Name: zipencrypt
Version: 0.3.0
Summary: Encryption for zipfile
Home-page: https://github.com/devthat/zipencrypt
Author: Jonathan Koch
Author-email: devthat@mailbox.org
License: UNKNOWN
Keywords: zipfile encryption zip password write writestr
Platform: UNKNOWN
Classifier: Development Status :: 3 - Alpha
Classifier: Programming Language :: Python
Classifier: Programming Language :: Python :: 2.7
Classifier: Programming Language :: Python :: 3.4
Classifier: Programming Language :: Python :: 3.5
Classifier: Programming Language :: Python :: 3.6
Classifier: Intended Audience :: Developers
Classifier: Operating System :: OS Independent
Classifier: Topic :: System :: Archiving :: Compression
Classifier: Topic :: Software Development :: Libraries :: Python Modules
